laam/__init__.py
laam/__main__.py
laam/exceptions.py
laam/utils.py
laam/commands/__init__.py
laam/commands/dut.py
laam/commands/files.py
laam/commands/identities.py
laam/commands/laacli.py
laam/commands/network.py
laam/commands/serials.py
laam/commands/services.py
laam/commands/system.py
laam/commands/usbs.py
laam/commands/workers.py
laam-0.8.3.dist-info/METADATA
laam-0.8.3.dist-info/WHEEL
laam-0.8.3.dist-info/entry_points.txt
laam-0.8.3.dist-info/top_level.txt
laam-0.8.3.dist-info/RECORD
