Metadata-Version: 2.4
Name: laam
Version: 0.8.3
Summary: LAA remote control
Author-email: Rémi Duraffort <remi.duraffort@linaro.org>
Maintainer-email: Rémi Duraffort <remi.duraffort@linaro.org>
License-Expression: MIT
Project-URL: Homepage, https://lavacloud.io
Project-URL: Documentation, https://docs.lavacloud.io
Project-URL: Repository, https://gitlab.com/LinaroLtd/lava/appliance/laam
Project-URL: Issues, https://gitlab.com/LinaroLtd/lava/appliance/laam/-/issues
Keywords: LAA,Embedded system,DUT
Classifier: Development Status :: 4 - Beta
Classifier: Environment :: Console
Classifier: Intended Audience :: Developers
Classifier: Natural Language :: English
Classifier: Programming Language :: Python :: 3
Classifier: Programming Language :: Python :: 3.9
Classifier: Programming Language :: Python :: 3.10
Classifier: Programming Language :: Python :: 3.11
Classifier: Programming Language :: Python :: 3.12
Classifier: Programming Language :: Python :: 3.13
Classifier: Programming Language :: Python :: 3.14
Classifier: Topic :: Software Development :: Embedded Systems
Classifier: Topic :: Software Development :: Testing
Classifier: Topic :: Terminals :: Serial
Requires-Python: >=3.9
Requires-Dist: aiohttp>=3.11.14
Requires-Dist: pexpect>=4.9.0
Requires-Dist: pyyaml>=6.0.2
Requires-Dist: requests>=2.32.3
Requires-Dist: requests-toolbelt>=1.0.0
Requires-Dist: websocket-client
Requires-Dist: yarl>=1.20.1
